codex/__init__.py
codex/all_tests.py
codex/ems/__init__.py
codex/ems/continuous.py
codex/ems/deep_factorized.py
codex/ems/deep_factorized_test.py
codex/ems/distribution.py
codex/ems/distribution_test.py
codex/ops/__init__.py
codex/ops/rounding.py
codex/ops/rounding_test.py
jax_codex-0.0.1.dist-info/LICENSE
jax_codex-0.0.1.dist-info/WHEEL
jax_codex-0.0.1.dist-info/METADATA
jax_codex-0.0.1.dist-info/RECORD
