Metadata-Version: 2.1
Name: jax-codex
Version: 0.0.1
Summary: COders and DEcoders for jaX.
Keywords: compression,data-compression,machine-learning,deep-learning
Author: CoDeX authors
Maintainer-email: Johannes Ballé <jballe@google.com>
Requires-Python: >=3.7
Classifier: Development Status :: 2 - Pre-Alpha
Classifier: Programming Language :: Python :: 3
Classifier: Programming Language :: Python :: 3 :: Only
Classifier: License :: OSI Approved :: Apache Software License
Classifier: Intended Audience :: Developers
Classifier: Intended Audience :: Education
Classifier: Intended Audience :: Science/Research
Classifier: Topic :: Scientific/Engineering :: Mathematics
Classifier: Topic :: Software Development :: Libraries :: Python Modules
Classifier: Topic :: Software Development :: Libraries
Requires-Dist: flax ~= 0.6
Requires-Dist: jax ~= 0.3
Project-URL: homepage, https://github.com/google/codex
Project-URL: repository, https://github.com/google/codex
